LICENSE
MANIFEST.in
README.rst
setup.py
tests.py
jsonobjects/__init__.py
jsonobjects/exceptions.py
jsonobjects/fields.py
jsonobjects/path.py
jsonobjects/schema.py
jsonobjects/utils.py
jsonobjects/validators.py
jsonobjects.egg-info/PKG-INFO
jsonobjects.egg-info/SOURCES.txt
jsonobjects.egg-info/dependency_links.txt
jsonobjects.egg-info/top_level.txt