Metadata-Version: 1.1
Name: jsonobjects
Version: 1.0.0
Summary: JSONObjects allows you to declaratively specify how to extract and convert elements from a JSON document.
Home-page: https://github.com/caxap/jsonobjects
Author: Maxim Kamenkov
Author-email: mkamenkov@gmail.com
License: MIT
Platform: UNKNOWN
Classifier: Development Status :: 5 - Production/Stable
Classifier: Framework :: Django
Classifier: Intended Audience :: Developers
Classifier: Natural Language :: English
Classifier: License :: OSI Approved :: MIT License
Classifier: Programming Language :: Python
Classifier: Programming Language :: Python :: 2.6
Classifier: Programming Language :: Python :: 2.7
Classifier: Programming Language :: Python :: 3
Classifier: Programming Language :: Python :: 3.3
Classifier: Programming Language :: Python :: 3.4
